AUTHORS
CHANGELOG.txt
DESCRIPTION
LICENSE
MANIFEST.in
README.rst
setup.py
django_ics_generator.egg-info/PKG-INFO
django_ics_generator.egg-info/SOURCES.txt
django_ics_generator.egg-info/dependency_links.txt
django_ics_generator.egg-info/top_level.txt
ics_generator/.__init__.py.swp
ics_generator/.urls.py.swp
ics_generator/__init__.py
ics_generator/models.py
ics_generator/urls.py
ics_generator/views.py
ics_generator/tests/.test_settings.py.swp
ics_generator/tests/__init__.py
ics_generator/tests/runtests.py
ics_generator/tests/south_settings.py
ics_generator/tests/test_settings.py
ics_generator/tests/urls.py
ics_generator/tests/views_tests.py