Metadata-Version: 1.0
Name: django-ics-generator
Version: 0.1.1
Summary: Django app to return an .ics file when called via http://www.keith-wood.name/icalendar.html 
